mqss/__init__.py
mqss/qiskit_adapter/__init__.py
mqss/qiskit_adapter/adapter.py
mqss/qiskit_adapter/backend.py
mqss/qiskit_adapter/job.py
mqss/qiskit_adapter/mqss_resources.py
mqss_qiskit-0.2.0.dist-info/METADATA
mqss_qiskit-0.2.0.dist-info/WHEEL
mqss_qiskit-0.2.0.dist-info/entry_points.txt
mqss_qiskit-0.2.0.dist-info/licenses/LICENSE
mqss_qiskit-0.2.0.dist-info/RECORD
